streamserver/__init__.py
streamserver/streamviewer.py
streamserver/viewer_mini.html
streamserver/samples/__init__.py
streamserver/samples/ss_cv2.py
streamserver/samples/ss_imageio.py
streamserver/samples/exclude/__init__.py
streamserver/samples/exclude/ss_pygame.py
streamserver-0.4.0.dist-info/LICENSE.md
streamserver-0.4.0.dist-info/METADATA
streamserver-0.4.0.dist-info/WHEEL
streamserver-0.4.0.dist-info/entry_points.txt
streamserver-0.4.0.dist-info/top_level.txt
streamserver-0.4.0.dist-info/RECORD
