Metadata-Version: 2.1
Name: streamserver
Version: 0.4.0
Summary: Server to stream multi-part images over HTTP
Home-page: UNKNOWN
Author: Soeren Rasmussen
License: Apache License, Version 2.0
Platform: UNKNOWN
Classifier: Development Status :: 4 - Beta
Classifier: Environment :: Console
Classifier: Intended Audience :: End Users/Desktop
Classifier: Intended Audience :: Developers
Classifier: License :: OSI Approved :: Apache Software License
Classifier: Operating System :: MacOS :: MacOS X
Classifier: Operating System :: Microsoft :: Windows
Classifier: Operating System :: POSIX
Classifier: Operating System :: OS Independent
Classifier: Programming Language :: Python :: 3
Classifier: Natural Language :: English
Requires-Python: >=3
Requires-Dist: numpy
Requires-Dist: imageio
Requires-Dist: IPython
